Metadata-Version: 2.1
Name: turing-demo-lib
Version: 2.1.0
Summary: A lightweight third-party turing_demo_lib/turing_demo_lib library
Home-page: https://github.com/lj-michale/turing_demo_lib
Author: lj.michale
Author-email: economic_luojie@outlook.com
License: Apache 2.0
Keywords: turing,turing_demo_lib,demo_lib,lib
Platform: UNKNOWN
Classifier: Development Status :: 3 - Alpha
Classifier: Intended Audience :: Developers
Classifier: Programming Language :: Python :: 3
Classifier: Programming Language :: Python :: 3.7
Classifier: Programming Language :: Python :: 3.8
Classifier: Programming Language :: Python :: 3.9
Classifier: Programming Language :: Python :: 3.10
Classifier: Programming Language :: Python :: 3 :: Only
Classifier: License :: OSI Approved :: MIT License
Classifier: Operating System :: OS Independent
Requires-Python: >=3.6
License-File: LICENSE
